matplotlib_autolayout
