Metadata-Version: 2.1
Name: matplotlib-autolayout
Version: 0.0.4
Summary: Auto layouts for matplotlib multiplots
Home-page: https://github.com/ericspring08/matplotlib-autolayout
Author: Eric Zhang
Author-email: ericspring08@gmail.com
Requires-Python: >=3.6
Requires-Dist: matplotlib
Requires-Dist: numpy
